LICENSE
README.md
setup.cfg
setup.py
px_django_upload.egg-info/PKG-INFO
px_django_upload.egg-info/SOURCES.txt
px_django_upload.egg-info/dependency_links.txt
px_django_upload.egg-info/requires.txt
px_django_upload.egg-info/top_level.txt
pxd_upload/__init__.py
pxd_upload/apps.py
pxd_upload/client.py
pxd_upload/conf.py
pxd_upload/const.py
pxd_upload/exceptions.py
pxd_upload/forms.py
pxd_upload/models.py
pxd_upload/signals.py
pxd_upload/utils.py
pxd_upload/views.py
pxd_upload/migrations/0001_initial.py
pxd_upload/migrations/__init__.py